dikas-package/__init__.py
dikas-package/hello.py
dikaspackage/__init__.py
dikaspackage/hello.py
dikaspackforeva-0.0.2.dist-info/METADATA
dikaspackforeva-0.0.2.dist-info/WHEEL
dikaspackforeva-0.0.2.dist-info/entry_points.txt
dikaspackforeva-0.0.2.dist-info/top_level.txt
dikaspackforeva-0.0.2.dist-info/RECORD
