Metadata-Version: 2.1
Name: dikaspackforeva
Version: 0.0.2
Summary: dikas project
Home-page: UNKNOWN
Author: dika foreva
Author-email: <goga.samunashvili@yahoo.com>
License: UNKNOWN
Keywords: python,video,stream,video stream,camera stream,sockets
Platform: UNKNOWN
Classifier: Development Status :: 1 - Planning
Classifier: Intended Audience :: Developers
Classifier: Programming Language :: Python :: 3
Classifier: Operating System :: Unix
Classifier: Operating System :: MacOS :: MacOS X
Classifier: Operating System :: Microsoft :: Windows
Requires-Dist: psutil
